flowjson/__init__.py
flowjson/main.py
flowjson/types/index.py
flowjson/types/workflows.py
flowjson/utils/execRun.py
flowjson/utils/executor.py
flowjson/utils/file.py
flowjson/utils/findOnScreen.py
flowjson/utils/formatArgument.py
flowjson/utils/formatOcrTextWithLayout.py
flowjson/utils/getAbsPath.py
flowjson/utils/img.py
flowjson/utils/imgEnsure.py
flowjson/utils/imgOcr.py
flowjson/utils/index.py
flowjson/utils/pathResolve.py
flowjson/utils/paths.py
flowjson/utils/pointOperation.py
flowjson/utils/printDebug.py
flowjson/utils/screenshot.py
flowjson/utils/typewrite.py
flowjson/utils/vCode.py
pyautogui_flowjson-0.1.2.dist-info/METADATA
pyautogui_flowjson-0.1.2.dist-info/WHEEL
pyautogui_flowjson-0.1.2.dist-info/entry_points.txt
pyautogui_flowjson-0.1.2.dist-info/RECORD
