Metadata-Version: 2.4
Name: pyautogui-flowjson
Version: 0.1.2
Summary: Use json5 for view-based workflows configuration
Author-email: qixiaqi <154809748@qq.com>
Requires-Python: >=3.9.9
Requires-Dist: aiofiles~=24.1.0
Requires-Dist: aiohttp>=3.11.18
Requires-Dist: ddddocr>=1.5.6
Requires-Dist: json5~=0.10.0
Requires-Dist: numpy~=2.0.2
Requires-Dist: opencv-python~=4.11.0.86
Requires-Dist: paddleocr>=2.10.0
Requires-Dist: paddlepaddle==3.0.0rc1
Requires-Dist: pillow>=11.2.1
Requires-Dist: pyautogui~=0.9.54
Requires-Dist: pydash~=8.0.5
Requires-Dist: pynput~=1.8.1
Requires-Dist: pyperclip>=1.9.0
Requires-Dist: pyscreeze~=1.0.1
